x_metaformer/__init__.py
x_metaformer/metaformer.py
x_metaformer/misc.py
x_metaformer/layers/__init__.py
x_metaformer/layers/act_layers.py
x_metaformer/layers/attention_layers.py
x_metaformer/layers/conv_layers.py
x_metaformer/layers/mixing_layers.py
x_metaformer/layers/mlp_layers.py
x_metaformer/layers/norm_layers.py
x_metaformer/pretraining/__init__.py
x_metaformer/pretraining/barlowtwins.py
x_metaformer/pretraining/mocov3.py
x_metaformer/pretraining/vicreg.py
x_Metaformer-0.3.1.dist-info/LICENSE
x_Metaformer-0.3.1.dist-info/METADATA
x_Metaformer-0.3.1.dist-info/WHEEL
x_Metaformer-0.3.1.dist-info/top_level.txt
x_Metaformer-0.3.1.dist-info/RECORD
