Metadata-Version: 2.1
Name: x-Metaformer
Version: 0.3.1
Summary: A PyTorch implementation of "MetaFormer Baselines" with optional extensions.
Home-page: https://github.com/romue404/x-metaformer
Author: Robert Müller
Author-email: robert.mueller1990@googlemail.com
License: MIT
Keywords: artificial intelligence,pytorch,metaformer,transformer,attention,convolutions
Classifier: Development Status :: 4 - Beta
Classifier: Intended Audience :: Developers
Classifier: Topic :: Scientific/Engineering :: Artificial Intelligence
Classifier: License :: OSI Approved :: MIT License
Classifier: Programming Language :: Python :: 3.6
License-File: LICENSE
Requires-Dist: torch (>=1.6)
Requires-Dist: numpy
